hakuriver/__init__.py
hakuriver/cli/__init__.py
hakuriver/cli/client.py
hakuriver/cli/docker.py
hakuriver/cli/docker_shell.py
hakuriver/cli/host.py
hakuriver/cli/init.py
hakuriver/cli/runner.py
hakuriver/cli/ssh.py
hakuriver/cli/task.py
hakuriver/cli/vps.py
hakuriver/core/__init__.py
hakuriver/core/client.py
hakuriver/core/config.py
hakuriver/core/host.py
hakuriver/core/models.py
hakuriver/core/runner.py
hakuriver/core/docker/__init__.py
hakuriver/core/docker/host_api.py
hakuriver/core/docker/host_terminal.py
hakuriver/core/docker/models.py
hakuriver/core/ssh_proxy/__init__.py
hakuriver/core/ssh_proxy/bind_connection.py
hakuriver/core/ssh_proxy/client.py
hakuriver/core/ssh_proxy/host.py
hakuriver/db/__init__.py
hakuriver/db/models.py
hakuriver/utils/__init__.py
hakuriver/utils/binding.py
hakuriver/utils/cli.py
hakuriver/utils/config_loader.py
hakuriver/utils/docker.py
hakuriver/utils/gpu.py
hakuriver/utils/logger.py
hakuriver/utils/snowflake.py
hakuriver/utils/ssh_key.py
hakuriver-0.3.0.dist-info/licenses/LICENSE
hakurun/__init__.py
hakurun/logger.py
hakurun/run.py
hakuriver-0.3.0.dist-info/METADATA
hakuriver-0.3.0.dist-info/WHEEL
hakuriver-0.3.0.dist-info/entry_points.txt
hakuriver-0.3.0.dist-info/top_level.txt
hakuriver-0.3.0.dist-info/RECORD
