Metadata-Version: 2.4
Name: hakuriver
Version: 0.3.0
Summary: A lightweight clustering tool with Docker container as virtual env.
Author-email: "Shih-Ying Yeh(KohakuBlueLeaf)" <apolloyeh0123@gmail.com>
Project-URL: Homepage, https://github.com/KohakuBlueleaf/HakuRiver
Project-URL: Repository, https://github.com/KohakuBlueleaf/HakuRiver
Requires-Python: >=3.10
License-File: LICENSE
Requires-Dist: hakustore
Requires-Dist: peewee
Requires-Dist: fastapi
Requires-Dist: httpx
Requires-Dist: psutil
Requires-Dist: toml
Requires-Dist: uvicorn[standard]
Requires-Dist: snowflake-id
Requires-Dist: docker
Requires-Dist: websockets
Provides-Extra: gpu
Requires-Dist: pynvml; extra == "gpu"
Dynamic: license-file
